pyinstantcrawl/__init__.py
pyinstantcrawl/main.py
pyinstantcrawl/pyinstantcrawl.py
pyinstantcrawl-1.0.1.dist-info/DESCRIPTION.rst
pyinstantcrawl-1.0.1.dist-info/METADATA
pyinstantcrawl-1.0.1.dist-info/RECORD
pyinstantcrawl-1.0.1.dist-info/WHEEL
pyinstantcrawl-1.0.1.dist-info/entry_points.txt
pyinstantcrawl-1.0.1.dist-info/metadata.json
pyinstantcrawl-1.0.1.dist-info/top_level.txt
