Metadata-Version: 2.0
Name: pyinstantcrawl
Version: 1.0.1
Summary: scrape a website with json template
Home-page: https://github.com/ihfazhillah/py-instant-crawl
Author: ihfazhillah
Author-email: me@ihfazh.com
License: MIT
Platform: UNKNOWN
Classifier: Development Status :: 4 - Beta
Classifier: Programming Language :: Python :: 3 :: Only
Requires-Dist: Click (==7.0)
Requires-Dist: parsel (==1.5.1)
Requires-Dist: requests (==2.21.0)
